gemlog_from_rss/__init__.py
gemlog_from_rss/examples.py
gemlog_from_rss/spip/__init__.py
gemlog_from_rss/spip/content.py
gemlog_from_rss/spip/page.py
gemlog_from_rss/wordpress/__init__.py
gemlog_from_rss-0.1.0.dist-info/LICENSE
gemlog_from_rss-0.1.0.dist-info/METADATA
gemlog_from_rss-0.1.0.dist-info/WHEEL
gemlog_from_rss-0.1.0.dist-info/top_level.txt
gemlog_from_rss-0.1.0.dist-info/RECORD
