Metadata-Version: 2.1
Name: gemlog-from-rss
Version: 0.1.0
Summary: A package that allows for converting RSS feeds into Gemlogs (Gemini blogs).
Home-page: https://github.com/Hookz/Gemlog-from-RSS
Author: Michal Jarski
Author-email: michal@jarski.eu
License: UNKNOWN
Keywords: gemini gemlog rss converter gemini-protocol xml
Platform: UNKNOWN
Requires-Python: >=3.8
Requires-Dist: requests (~=2.25.1)
Requires-Dist: lxml (~=4.6.2)
Requires-Dist: beautifulsoup4 (~=4.9.3) ; python_version == "3.8"
